yt_dlp_bonus/__init__.py
yt_dlp_bonus/__main__.py
yt_dlp_bonus/cli.py
yt_dlp_bonus/constants.py
yt_dlp_bonus/exceptions.py
yt_dlp_bonus/main.py
yt_dlp_bonus/models.py
yt_dlp_bonus/utils.py
yt_dlp_bonus-0.2.5.dist-info/licenses/LICENSE
yt_dlp_bonus-0.2.5.dist-info/METADATA
yt_dlp_bonus-0.2.5.dist-info/WHEEL
yt_dlp_bonus-0.2.5.dist-info/entry_points.txt
yt_dlp_bonus-0.2.5.dist-info/top_level.txt
yt_dlp_bonus-0.2.5.dist-info/RECORD
