Metadata-Version: 2.4
Name: yt-dlp-bonus
Version: 0.2.5
Summary: An extension of yt-dlp targeting YoutubeDL with pydantic support.
Home-page: https://github.com/Simatwa/yt-dlp-bonus
Author: Smartwa
Author-email: simatwacaleb@proton.me
Maintainer: Smartwa
License: The Unlicense
Project-URL: Bug Report, https://github.com/Simatwa/yt-dlp-bonus/issues/new
Project-URL: Homepage, https://github.com/Simatwa/yt-dlp-bonus
Project-URL: Source Code, https://github.com/Simatwa/yt-dlp-bonus
Project-URL: Issue Tracker, https://github.com/Simatwa/yt-dlp-bonus/issues
Project-URL: Download, https://github.com/Simatwa/yt-dlp-bonus/releases
Project-URL: Documentation, https://github.com/Simatwa/yt-dlp-bonus/
Keywords: yt-dlp,yt-dlp-bonus
Classifier: License :: OSI Approved :: The Unlicense (Unlicense)
Classifier: Intended Audience :: Developers
Classifier: License :: Free For Home Use
Classifier: Programming Language :: Python
Classifier: Topic :: Software Development :: Libraries :: Python Modules
Classifier: Programming Language :: Python :: 3 :: Only
Classifier: Programming Language :: Python :: 3.10
Classifier: Programming Language :: Python :: 3.11
Classifier: Programming Language :: Python :: 3.12
Classifier: Programming Language :: Python :: 3.13
Requires-Python: >=3.10
License-File: LICENSE
Requires-Dist: yt-dlp>=2025.7.21
Requires-Dist: pydantic>=2.11.7
Requires-Dist: typer>=0.16.0
Dynamic: author
Dynamic: author-email
Dynamic: classifier
Dynamic: description
Dynamic: description-content-type
Dynamic: home-page
Dynamic: keywords
Dynamic: license
Dynamic: license-file
Dynamic: maintainer
Dynamic: project-url
Dynamic: requires-dist
Dynamic: requires-python
Dynamic: summary
